{
  "Identity": 1000,
  "CategoryOrder": [
    "Site",
    "Pages",
    "CDN",
    "Email",
    "URLs",
    "References",
    "Encryption",
    "Skin",
    "Addons",
    "Meta",
    "Variables"
  ],
  "SiteDomain": "YetaWFDist5",
  "DefaultSiteDomain": "YetaWFDist5",
  "IsDefaultSite": true,
  "OriginalSiteDomain": "YetaWFDist5",
  "SiteTestDomain": null,
  "SiteName": "YetaWFDist5",
  "EnforceSiteUrl": false,
  "PageSecurity": 0,
  "EnforceSitePort": false,
  "PortNumberEval": 80,
  "PortNumber": 80,
  "PortNumberSSLEval": 443,
  "PortNumberSSL": 443,
  "SiteUrlHttp": "http://localhost:50000/",
  "SiteUrlHttps": "https://localhost:50000/",
  "Localization": true,
  "DefaultLanguageId": "en-US",
  "AllowAnonymousUsers": true,
  "Locked": false,
  "IsLocked": false,
  "LockedExternal": false,
  "IsLockedExternal": false,
  "LockedForIP": null,
  "LockedExternalForIP": null,
  "LockedUrl": "/Maintenance/Offline For Maintenance.html",
  "IsLockedAny": false,
  "AllowPopups": true,
  "CssNoTooltips": "linkpreview-show peelback",
  "FavIcon": null,
  "FavIcon_Data": "",
  "FavIconLrg": null,
  "FavIconLrg_Data": "",
  "FavIconLink": "",
  "Country": "United States",
  "TimeZone": null,
  "Currency": "USD",
  "CurrencyFormat": "$ #,0.00",
  "CurrencyDecimals": 2,
  "CopyrightEvaluated": "YetaWF.com - © Copyright 2019 Softel vdm, Inc.",
  "StaticPages": false,
  "DEBUGMODE": true,
  "DiagnosticsMode": true,
  "AllowCacheUse": true,
  "Compression": true,
  "CompressCSSFiles": true,
  "BundleCSSFiles": true,
  "CssLocation": 1,
  "CompressJSFiles": true,
  "BundleJSFiles": true,
  "JSLocation": 1,
  "DisableMinimizeFUOC": false,
  "IFrameUse": 0,
  "Copyright": "YetaWF.com - © Copyright \u003c\u003cYear\u003e\u003e Softel vdm, Inc.",
  "UseCDNComponents": false,
  "CanUseCDNComponents": false,
  "UseCDN": false,
  "CanUseCDN": false,
  "CDNUrl": null,
  "HaveCDNUrl": false,
  "CDNUrlSecure": null,
  "HaveCDNUrlSecure": false,
  "StaticDomain": null,
  "HaveStaticDomain": false,
  "CanUseStaticDomain": false,
  "EmailDebug": false,
  "AdminEmail": "youremail@YetaWFDist5",
  "SMTP": {
    "IsValid": true,
    "Server": "mail.YetaWFDist5",
    "Port": 25,
    "Authentication": 1,
    "UserName": "youremail@YetaWFDist5",
    "Password": "somepassword",
    "SSL": false,
    "SendTestEmail": null
  },
  "HomePageUrl": "/",
  "NotFoundUrl": "/Errors/404",
  "MobileSiteUrl": null,
  "UnsupportedBrowserUrl": "/Maintenance/Unsupported Browser.html",
  "LoginUrl": "/User/Login",
  "PostLoginUrl": null,
  "ExternalAccountSetupUrl": "/User/Setup External Account",
  "ReferencedModules": [],
  "SelectedSkin": {
    "Collection": "YetaWF/DefaultSkin/DefaultSkin",
    "FileName": "Default"
  },
  "SelectedPopupSkin": {
    "Collection": "YetaWF/DefaultSkin/DefaultSkin",
    "FileName": "Popup"
  },
  "FormErrorsImmed": false,
  "BootstrapSkin": "Bootstrap Default",
  "jQueryUISkin": "Start",
  "KendoUISkin": "Blue Opal",
  "TabStyle": 0,
  "PublicKey": "\u003cRSAKeyValue\u003e\u003cModulus\u003e0v3eDbSp7oajC6Po5kZWBvmi0dVQXklF9rRokgc9c1i7fhD9IIBHYUfkWikdReYJOKEY35whNV280oq4z+msI2ZZ8rvfkwcqDeXyS+mjQlbfSGwDu/Rda4dgqCxLAKIenwNMd8ZCMieR+rFHus55zKz4N02l24LBOswGt3NE6B0=\u003c/Modulus\u003e\u003cExponent\u003eAQAB\u003c/Exponent\u003e\u003cP\u003e\u003c/P\u003e\u003cQ\u003e\u003c/Q\u003e\u003cDP\u003e\u003c/DP\u003e\u003cDQ\u003e\u003c/DQ\u003e\u003cInverseQ\u003e\u003c/InverseQ\u003e\u003cD\u003e\u003c/D\u003e\u003c/RSAKeyValue\u003e",
  "PrivateKey": "\u003cRSAKeyValue\u003e\u003cModulus\u003e0v3eDbSp7oajC6Po5kZWBvmi0dVQXklF9rRokgc9c1i7fhD9IIBHYUfkWikdReYJOKEY35whNV280oq4z+msI2ZZ8rvfkwcqDeXyS+mjQlbfSGwDu/Rda4dgqCxLAKIenwNMd8ZCMieR+rFHus55zKz4N02l24LBOswGt3NE6B0=\u003c/Modulus\u003e\u003cExponent\u003eAQAB\u003c/Exponent\u003e\u003cP\u003e9punFYhXajNRy6j9X/G8FEN90kS8GGD5sV2zro+nalJFtlDVW5zVDqvjc0HiOUsCTC4TPWQk16nbLXjiITgVpw==\u003c/P\u003e\u003cQ\u003e2wb3jWAbzbD2E1qR/qLZv9a6cWwB0DBP122leOXNYMkzXgQOKzTg9ZtW+kgn0h6UnR8YOMcT4UxsUmdOJ8NUmw==\u003c/Q\u003e\u003cDP\u003e27A4Pb9zGEHVmVfXOHSyN18UpI/k/NbPOcmeu2BwJRBb2BnUqENjrilEe7XyoVWIG3NkYmlnRNSlU7H/yNYcuw==\u003c/DP\u003e\u003cDQ\u003eWFVb+3F6ZR9sbuvFG5wUE7GHKf00UgFaAfkflj2f8dvTUqRyDmzaGVPX5UK6hJx+tUt4GlX3p5KJ0UYGmDTH5w==\u003c/DQ\u003e\u003cInverseQ\u003eRUD5wAO0XEhu9TGicAzKnGIh3/x/+7dS8wGRh2BKbD2wgv9za3ey/aTxL6qdxPssXcvGli/Yc7IhjSVYj4BIpQ==\u003c/InverseQ\u003e\u003cD\u003eKkSTXHmJ5W/xb96JRMBocYNHG/Q44nqZWn/vxvlOVTI8dVff7cflBNcLJwi/hYY86KxVOE6l1HQP5LnHplcwlZWeWGmb8DJszuwKnZjZ+rND2SXK4nvojBLdRHQ6d4Y+ajYCQR+oYCYNzpCDisq5D5xAQuIK/lugnbburPtKt70=\u003c/D\u003e\u003c/RSAKeyValue\u003e",
  "Analytics": null,
  "AnalyticsContent": null,
  "GoogleVerification": null,
  "ExtraHead": null,
  "ExtraBodyTop": null,
  "ExtraBodyBottom": null,
  "UseGeoLocation": false,
  "SiteMetaTags": null,
  "PageMetaTags": null,
  "SiteMapPriority": 50,
  "DefaultChangeFrequency": 4,
  "ModuleControlServices": "96caead9-068d-4b83-8f46-5269834f3b16",
  "ModuleEditingServices": "acdc1453-32bd-4de2-ab2b-7bf5ce217762",
  "PackageLocalizationServices": "b30d6119-4769-4702-88d8-585ee4ebd4a7",
  "MenuServices": "59909bb1-75f4-419f-b961-8569bb282131",
  "ModuleControlServicesFallback": "96caead9-068d-4b83-8f46-5269834f3b16",
  "ModuleEditingServicesFallback": "acdc1453-32bd-4de2-ab2b-7bf5ce217762",
  "PackageLocalizationServicesFallback": "b30d6119-4769-4702-88d8-585ee4ebd4a7",
  "MenuServicesFallback": "59909bb1-75f4-419f-b961-8569bb282131",
  "PageEditingServices": "fbb3c6d3-fbd2-4ab1-bf0e-8716f3d1b052",
  "PageEditingServicesFallback": "fbb3c6d3-fbd2-4ab1-bf0e-8716f3d1b052",
  "CurrentYear": "2019"
}